{
  "name": "Iris Pink",
  "colors": {
    "editor.background": "#2C1E3C",
    "editor.foreground": "#FFDBE5",
    "editorLineNumber.foreground": "#5F4B8B",
    "editorCursor.foreground": "#E27396",
    "editor.selectionBackground": "#EA9AB260",
    "editor.inactiveSelectionBackground": "#EA9AB230",
    "editor.wordHighlightBackground": "#5F4B8B40",
    "editor.selectionHighlightBackground": "#E2739630",
    "activityBar.background": "#2C1E3C",
    "activityBar.foreground": "#FFDBE5",
    "activityBarBadge.background": "#E27396",
    "activityBarBadge.foreground": "#2C1E3C",
    "sideBar.background": "#37274D",
    "sideBar.foreground": "#FFDBE5",
    "sideBarSectionHeader.background": "#37274D",
    "sideBarTitle.foreground": "#FFDBE5",
    "editorGroupHeader.tabsBackground": "#37274D",
    "tab.activeBackground": "#2C1E3C",
    "tab.inactiveBackground": "#37274D",
    "tab.activeForeground": "#E27396",
    "tab.inactiveForeground": "#FFDBE5",
    "statusBar.background": "#5F4B8B",
    "statusBar.foreground": "#FFDBE5",
    "statusBar.noFolderBackground": "#5F4B8B",
    "statusBar.debuggingBackground": "#E27396",
    "statusBar.debuggingForeground": "#2C1E3C",
    "panel.background": "#2C1E3C",
    "panelTitle.activeForeground": "#E27396",
    "panelTitle.inactiveForeground": "#5F4B8B",
    "button.background": "#E27396",
    "button.foreground": "#2C1E3C",
    "list.hoverBackground": "#5F4B8B30",
    "list.activeSelectionBackground": "#5F4B8B50",
    "terminal.background": "#2C1E3C",
    "terminal.foreground": "#FFDBE5",
    "terminal.ansiBlack": "#2C1E3C",
    "terminal.ansiRed": "#E27396",
    "terminal.ansiGreen": "#6D9F71",
    "terminal.ansiYellow": "#EA9AB2",
    "terminal.ansiBlue": "#5F4B8B",
    "terminal.ansiMagenta": "#FFDBE5",
    "terminal.ansiCyan": "#337357",
    "terminal.ansiWhite": "#FFDBE5"
  },
  "tokenColors": [
    {
      "scope": ["comment", "punctuation.definition.comment"],
      "settings": {
        "foreground": "#337357",
        "fontStyle": "italic"
      }
    },
    {
      "scope": ["keyword", "storage", "modifier", "entity.name.tag"],
      "settings": {
        "foreground": "#5F4B8B"
      }
    },
    {
      "scope": ["variable", "entity.other.attribute-name"],
      "settings": {
        "foreground": "#EA9AB2"
      }
    },
    {
      "scope": ["string", "entity.name.type.class"],
      "settings": {
        "foreground": "#E27396"
      }
    },
    {
      "scope": [
        "entity.name.function",
        "support.function",
        "meta.function-call"
      ],
      "settings": {
        "foreground": "#6D9F71"
      }
    },
    {
      "scope": ["punctuation", "delimiter", "bracket"],
      "settings": {
        "foreground": "#FFDBE5"
      }
    },
    {
      "scope": ["operator"],
      "settings": {
        "foreground": "#6D9F71"
      }
    },
    {
      "scope": ["constant.numeric", "constant.language", "constant.boolean"],
      "settings": {
        "foreground": "#FFDBE5"
      }
    }
  ]
}
